<?xml version="1.0" encoding="UTF-8"?>
<monster name="Lickilicky" nameDescription="a Lickilicky" race="normal" experience="650" speed="217" manacost="0">
    <health now="140" max="140"/>
    <look type="3046" head="45" body="70" legs="95" feet="113" corpse="21629"/>
    <targetchange interval="2000" chance="0"/>
    <strategy attack="100" defense="0"/>
    <flags>
        <flag summonable="1"/>
        <flag attackable="1"/>
        <flag hostile="1"/>
        <flag passive="1"/>
        <flag illusionable="1"/>
        <flag convinceable="1"/>
        <flag pushable="1"/>
        <flag canpushitems="0"/>
        <flag canpushcreatures="0"/>
        <flag targetdistance="1"/>
        <flag staticattack="97"/>
        <flag runonhealth="0"/>
       
    </flags>
    <attacks>
        <attack name="melee" interval="2000" chance="100" range="1" min="-50" max="-100"/>
        <attack name="Lick" interval="2617" chance="30" range="1"/>
        <attack name="Squisky Licking" interval="2899" chance="29" range="4"/>
        <attack name="Stomp" interval="2946" chance="28" range="1"/>
        <attack name="Refresh" interval="4134" chance="8" range="6"/>
        <attack name="Gyro Ball" interval="5120" chance="20" range="3"/>
        <attack name="Body Slam" interval="5120" chance="25" range="3"/>
        <attack name="Magnitude" interval="5120" chance="23" range="5"/>
        <attack name="Zen Headbutt" interval="5120" chance="20" range="3"/>
        <attack name="Belch" interval="5120" chance="23" range="4"/>
        <attack name="Earthquake" interval="5120" chance="18" range="1"/>
        <attack name="Toxic" interval="5120" chance="20" range="1"/>		
    </attacks>
    <defenses armor="0" defense="0"/>
    <voices interval="5000" chance="10">
        <voice sentence="Lickilicky!"/>
    </voices>
    <loot>
        <item id="12179" chance="5000" count="1" countmax="1"/> --comb
        <item id="11453" chance="150" count="1" countmax="1"/> --heart stone
        <item id="12338" chance="100" count="1"/> --bag box --bag box
		        <item id="21998" chance="10" count="1"/> --bag box --bag box
    </loot>
    <script>
        <event name="Spawn"/>
    </script>
</monster>
